tvl_backends/pyav/__init__.py
tvl_backends_pyav-0.1.0b18.dist-info/LICENSE
tvl_backends_pyav-0.1.0b18.dist-info/METADATA
tvl_backends_pyav-0.1.0b18.dist-info/WHEEL
tvl_backends_pyav-0.1.0b18.dist-info/top_level.txt
tvl_backends_pyav-0.1.0b18.dist-info/RECORD
